{"name":"Allure Report","stats":{"total":8,"new":8,"skipped":3,"passed":5,"retries":2},"status":"passed","duration":102065,"createdAt":1770199997915,"plugin":"Awesome","newTests":[{"id":"15dc81bdf94f37ae14bf41a0925cd0cd","name":"Delete an existing client","status":"skipped","duration":1},{"id":"0cc7fe095c7d838d260a90d002c29a92","name":"Login via API","status":"passed","duration":2831},{"id":"95e1aab0301df6f18b26cd805da57663","name":"Update an existing client","status":"skipped","duration":3},{"id":"adda849085f9560909457e09c8e444b4","name":"Login via UI with valid credentials","status":"passed","duration":13083},{"id":"3e5ec373967c367efdafbd6ffa0dfd05","name":"Perform journal entry workflow - detailed steps","status":"skipped","duration":4},{"id":"f0f9242b9a0fbea914aba4873974ebff","name":"Create a new audit case","status":"passed","duration":30894},{"id":"50c8e9f2b8ee1a39a8b3ace750f138a1","name":"Create a new individual client","status":"passed","duration":25655},{"id":"1254f513df3d0302b38af0ab199cf1e5","name":"Create a new client","status":"passed","duration":29594}],"flakyTests":[],"retryTests":[],"pullRequestHref":"","jobHref":"https://gitea.dev.summa-ai.com/summa/Summa/actions/runs/11166"}