{"name":"Allure Report","stats":{"total":8,"retries":2,"new":8,"broken":2,"passed":3,"skipped":3},"status":"broken","duration":257334,"createdAt":1782832566081,"plugin":"Awesome","newTests":[{"id":"fae6e92994ea9666dd08f80669235c1e","name":"Create a new client","status":"broken","duration":100301},{"id":"9459d7ce09c979fd9f3f7d5d72ba3eec","name":"Login via API","status":"passed","duration":4130},{"id":"9a16de9da1f8cf6815dacd277e0a1b91","name":"Create a new individual client","status":"broken","duration":100825},{"id":"61ac2213eeb19568c8300002646ae5dd","name":"Delete an existing client","status":"skipped","duration":5},{"id":"99c9d38c6ce040b06baebc88a9727da9","name":"Perform journal entry workflow - detailed steps","status":"skipped","duration":3},{"id":"6144d5a35da65b6fe7a11d491ea3119e","name":"Update an existing client","status":"skipped","duration":4},{"id":"ae290241b5122d4c6cc0a34eb655ea3d","name":"Create a new audit case","status":"passed","duration":35425},{"id":"292fbcd4cd558aa96fd6b43e1e042870","name":"Login via UI with valid credentials","status":"passed","duration":16641}],"flakyTests":[],"retryTests":[],"pullRequestHref":"","jobHref":"https://gitea.dev.summa-ai.com/summa/Summa/actions/runs/19498"}