{"name":"Allure Report","stats":{"total":8,"new":8,"passed":5,"skipped":3,"retries":2},"status":"passed","duration":122082,"createdAt":1777924032313,"plugin":"Awesome","newTests":[{"id":"5b01a131cae3264efc9d73aa0349aedb","name":"Login via UI with valid credentials","status":"passed","duration":17306},{"id":"c6a34ee33bbdfce71de45f8d332e5f36","name":"Create a new client","status":"passed","duration":12057},{"id":"e2450350c48cdcb6895cda4fe8daf6c5","name":"Update an existing client","status":"skipped","duration":2},{"id":"99fab4abe082bec7e800e7eac63e8a11","name":"Login via API","status":"passed","duration":5136},{"id":"ae716bad29c4b0e228ffe519a1629b43","name":"Create a new audit case","status":"passed","duration":60449},{"id":"54fa728288bc82af3b1971249e9dc9e8","name":"Delete an existing client","status":"skipped","duration":1},{"id":"3ae420cc942534139d249e60e0ba6081","name":"Perform journal entry workflow - detailed steps","status":"skipped","duration":0},{"id":"4a0322eb909ea4869926887fc6e87859","name":"Create a new individual client","status":"passed","duration":27131}],"flakyTests":[],"retryTests":[],"pullRequestHref":"","jobHref":"https://gitea.dev.summa-ai.com/summa/Summa/actions/runs/16579"}