{"name":"Allure Report","stats":{"total":8,"new":8,"skipped":3,"retries":3,"passed":5},"status":"passed","duration":82911,"createdAt":1770380065270,"plugin":"Awesome","newTests":[{"id":"bd3320e4964fad195f4112840f35707a","name":"Delete an existing client","status":"skipped","duration":3},{"id":"0658757e220bc0e9e0c6e39f96c7db7e","name":"Create a new client","status":"passed","duration":25698},{"id":"9385aeb17fcc93825a60da11c5148f04","name":"Login via UI with valid credentials","status":"passed","duration":9249},{"id":"1a07961e62fc0c42bc72410a36b940a0","name":"Login via API","status":"passed","duration":1365},{"id":"444b692357278e284a608350bec696a3","name":"Perform journal entry workflow - detailed steps","status":"skipped","duration":1},{"id":"a7ef29e85292c5712a21000347108680","name":"Create a new individual client","status":"passed","duration":14680},{"id":"3df3fdff2a0957201188de4510c45878","name":"Create a new audit case","status":"passed","duration":31913},{"id":"74d534e6c9adf0bc4fadbfc37024121a","name":"Update an existing client","status":"skipped","duration":2}],"flakyTests":[],"retryTests":[],"pullRequestHref":"","jobHref":"https://gitea.dev.summa-ai.com/summa/Summa/actions/runs/11350"}