{"name":"Allure Report","stats":{"total":8,"retries":2,"new":8,"passed":5,"skipped":3},"status":"passed","duration":96711,"createdAt":1775829088265,"plugin":"Awesome","newTests":[{"id":"e849729f7df6a7234da7061c86bfd9c9","name":"Create a new individual client","status":"passed","duration":19869},{"id":"874fac3eb2410d4770cdc016b0a74067","name":"Delete an existing client","status":"skipped","duration":0},{"id":"2c9078ea4cceac25d4261cbdc4b987bf","name":"Login via UI with valid credentials","status":"passed","duration":13469},{"id":"44f6d52d618b8c2372079f46bd34e368","name":"Update an existing client","status":"skipped","duration":1},{"id":"3873cdf836041e162fc120bfcb837470","name":"Create a new audit case","status":"passed","duration":36576},{"id":"00cf124d21a3f0216bc00025f616aabf","name":"Perform journal entry workflow - detailed steps","status":"skipped","duration":1},{"id":"32f67198e807c32c8765841baff479af","name":"Login via API","status":"passed","duration":3348},{"id":"5304a0957086ce7294c64a0ede5fecb8","name":"Create a new client","status":"passed","duration":23447}],"flakyTests":[],"retryTests":[],"pullRequestHref":"","jobHref":"https://gitea.dev.summa-ai.com/summa/Summa/actions/runs/14769"}